README.md
aquachain-kv
setup.py
aquachain_kv.egg-info/PKG-INFO
aquachain_kv.egg-info/SOURCES.txt
aquachain_kv.egg-info/dependency_links.txt
aquachain_kv.egg-info/requires.txt
aquachain_kv.egg-info/top_level.txt
aquachainkv/__init__.py
aquachainkv/aquachain.kv
aquachainkv/aquasettings.py
img/aquachain.png