Metadata-Version: 1.1
Name: aquachain-kv
Version: 0.0.1
Summary: Aquachain GUI wallet
Home-page: https://github.com/aquachain/aquachain-kv
Author: Aquachain Authors
Author-email: aquachain@riseup.net
License: GPL
Platform: UNKNOWN
Classifier: Development Status :: 2 - Pre-Alpha
Classifier: License :: Free for non-commercial use
Classifier: License :: OSI Approved :: GNU General Public License (GPL)
